{
    "value": [
    {
      "_id": "666f5e3705d7d748cc793498",
      "index": 0,
      "guid": "b55b1b37-91e1-4af1-9e79-54d17156c2be",
      "isActive": false,
      "balance": "$2,546.29",
      "picture": "http://placehold.it/32x32",
      "age": 24,
      "eyeColor": "blue",
      "name": "Watson Mccray",
      "gender": "male",
      "company": "ROUGHIES",
      "email": "watsonmccray@roughies.com",
      "phone": "+1 (954) 578-3579",
      "address": "115 Celeste Court, Naomi, West Virginia, 4453",
      "about": "Consequat ex dolore proident ipsum ea elit eu anim qui adipisicing. Labore magna ea ad deserunt reprehenderit anim ea ut consectetur ullamco aliqua. Cupidatat deserunt commodo nulla dolor aliquip tempor cupidatat incididunt eiusmod.\r\n",
      "registered": "2015-12-07T10:35:08 -01:00",
      "latitude": 74.073535,
      "longitude": 177.759484,
      "tags": [
        "consectetur",
        "laborum",
        "ullamco",
        "qui",
        "velit",
        "fugiat",
        "est"
      ],
      "friends": [
        {
          "id": 0,
          "name": "Connie Burt"
        },
        {
          "id": 1,
          "name": "Whitehead Randall"
        },
        {
          "id": 2,
          "name": "Gill Harrison"
        }
      ],
      "greeting": "Hello, Watson Mccray! You have 6 unread messages.",
      "favoriteFruit": "banana"
    },
    {
      "_id": "666f5e37e4b08f7a5c11fcc5",
      "index": 1,
      "guid": "9a09126d-aecc-4ea8-b346-c0f432b755ad",
      "isActive": true,
      "balance": "$3,604.19",
      "picture": "http://placehold.it/32x32",
      "age": 36,
      "eyeColor": "brown",
      "name": "Florence Morton",
      "gender": "female",
      "company": "DOGSPA",
      "email": "florencemorton@dogspa.com",
      "phone": "+1 (853) 544-2166",
      "address": "256 Rutherford Place, Summerset, California, 1313",
      "about": "Sit sit ipsum sunt ipsum ullamco est magna proident. Enim non veniam mollit labore id eiusmod nulla aliquip officia adipisicing laborum deserunt anim amet. Ad mollit proident incididunt eu esse. Occaecat enim velit cillum eu sit exercitation labore. Eiusmod quis officia Lorem sunt commodo mollit sit tempor minim proident occaecat.\r\n",
      "registered": "2022-10-19T11:56:22 -02:00",
      "latitude": 60.129416,
      "longitude": 26.846814,
      "tags": [
        "sint",
        "incididunt",
        "et",
        "voluptate",
        "in",
        "consequat",
        "minim"
      ],
      "friends": [
        {
          "id": 0,
          "name": "Elvia Decker"
        },
        {
          "id": 1,
          "name": "Sears Huber"
        },
        {
          "id": 2,
          "name": "Valarie King"
        }
      ],
      "greeting": "Hello, Florence Morton! You have 9 unread messages.",
      "favoriteFruit": "banana"
    },
    {
      "_id": "666f5e37d5d9b03fda2c8a31",
      "index": 2,
      "guid": "39ed1e12-cba2-4e16-895a-68f240264858",
      "isActive": true,
      "balance": "$1,361.82",
      "picture": "http://placehold.it/32x32",
      "age": 29,
      "eyeColor": "green",
      "name": "Lavonne Vaughn",
      "gender": "female",
      "company": "EZENTIA",
      "email": "lavonnevaughn@ezentia.com",
      "phone": "+1 (984) 463-3422",
      "address": "438 Commerce Street, Brownlee, Nebraska, 3714",
      "about": "In ipsum consequat aute nulla enim id consectetur. Voluptate laboris excepteur irure excepteur deserunt do enim consectetur. Occaecat non irure anim ad aliquip sit labore in. Cillum quis nulla pariatur aliqua veniam dolor pariatur dolor reprehenderit dolor irure.\r\n",
      "registered": "2023-05-20T11:59:45 -02:00",
      "latitude": -53.902724,
      "longitude": -38.494156,
      "tags": [
        "do",
        "commodo",
        "incididunt",
        "culpa",
        "ullamco",
        "in",
        "excepteur"
      ],
      "friends": [
        {
          "id": 0,
          "name": "Becky Craft"
        },
        {
          "id": 1,
          "name": "Ortiz George"
        },
        {
          "id": 2,
          "name": "Giles Landry"
        }
      ],
      "greeting": "Hello, Lavonne Vaughn! You have 2 unread messages.",
      "favoriteFruit": "strawberry"
    },
    {
      "_id": "666f5e371c3200a274c6ea66",
      "index": 3,
      "guid": "619a86d5-b891-481d-b188-bcdc279c9184",
      "isActive": false,
      "balance": "$2,180.51",
      "picture": "http://placehold.it/32x32",
      "age": 30,
      "eyeColor": "blue",
      "name": "Cassandra Waters",
      "gender": "female",
      "company": "MIXERS",
      "email": "cassandrawaters@mixers.com",
      "phone": "+1 (884) 535-3122",
      "address": "304 Bethel Loop, Singer, Indiana, 4109",
      "about": "Incididunt enim incididunt eiusmod magna deserunt commodo esse. Incididunt cillum mollit anim aliquip tempor nostrud tempor aute dolore. Minim velit laborum nostrud ut consectetur non enim dolor. Quis do culpa culpa velit. Mollit commodo occaecat nostrud irure mollit nulla ad commodo quis esse ipsum. Dolore esse reprehenderit cupidatat magna minim aliqua cupidatat duis irure nulla minim. Fugiat qui aute laborum do.\r\n",
      "registered": "2023-07-07T05:55:01 -02:00",
      "latitude": -15.247878,
      "longitude": -115.536121,
      "tags": [
        "cupidatat",
        "ea",
        "consequat",
        "sint",
        "consectetur",
        "exercitation",
        "labore"
      ],
      "friends": [
        {
          "id": 0,
          "name": "Chelsea Kim"
        },
        {
          "id": 1,
          "name": "House Herrera"
        },
        {
          "id": 2,
          "name": "Adrian Stewart"
        }
      ],
      "greeting": "Hello, Cassandra Waters! You have 8 unread messages.",
      "favoriteFruit": "banana"
    },
    {
      "_id": "666f5e371f433ff6d1a3c32c",
      "index": 4,
      "guid": "d9091efe-f264-4603-8286-136bef41a12f",
      "isActive": false,
      "balance": "$3,975.10",
      "picture": "http://placehold.it/32x32",
      "age": 25,
      "eyeColor": "green",
      "name": "Hayes Herman",
      "gender": "male",
      "company": "NEUROCELL",
      "email": "hayesherman@neurocell.com",
      "phone": "+1 (928) 581-3525",
      "address": "372 Abbey Court, Crayne, Hawaii, 5898",
      "about": "Ipsum anim elit dolor qui esse enim aliqua enim sunt dolore irure mollit dolore. Elit non occaecat fugiat consequat occaecat voluptate elit ut mollit esse laborum laboris. Amet cupidatat ullamco laborum deserunt anim elit mollit in dolor et tempor anim enim. Ut irure magna esse dolor. Dolor fugiat deserunt labore proident mollit dolore. Irure eu exercitation sit irure velit. Aliquip veniam nisi amet occaecat sint ut.\r\n",
      "registered": "2019-01-28T11:17:30 -01:00",
      "latitude": -53.125677,
      "longitude": 102.954395,
      "tags": [
        "excepteur",
        "in",
        "labore",
        "commodo",
        "exercitation",
        "deserunt",
        "magna"
      ],
      "friends": [
        {
          "id": 0,
          "name": "Chasity Guerrero"
        },
        {
          "id": 1,
          "name": "Araceli Pacheco"
        },
        {
          "id": 2,
          "name": "Augusta House"
        }
      ],
      "greeting": "Hello, Hayes Herman! You have 9 unread messages.",
      "favoriteFruit": "apple"
    },
    {
      "_id": "666f5e37422bfa283de36d3e",
      "index": 5,
      "guid": "528ed2c9-c917-4ec1-aec8-2feafbde73b6",
      "isActive": true,
      "balance": "$1,668.18",
      "picture": "http://placehold.it/32x32",
      "age": 24,
      "eyeColor": "green",
      "name": "Rachelle Chavez",
      "gender": "female",
      "company": "FUELTON",
      "email": "rachellechavez@fuelton.com",
      "phone": "+1 (975) 535-3227",
      "address": "452 Lorraine Street, Ezel, Ohio, 5523",
      "about": "Eiusmod cillum nisi veniam sunt adipisicing. Reprehenderit fugiat eu proident commodo reprehenderit ad non culpa sit laboris officia. Minim sit ut amet mollit eiusmod laborum cillum sit culpa aliqua aliquip nostrud nulla deserunt. Excepteur eiusmod fugiat duis aliquip. Veniam proident aute laborum minim exercitation culpa labore ullamco excepteur nisi magna. Nulla velit deserunt ipsum aliquip sit consectetur voluptate culpa dolore. Ex quis deserunt cillum proident tempor ullamco.\r\n",
      "registered": "2022-01-17T10:14:48 -01:00",
      "latitude": -22.33497,
      "longitude": -99.832018,
      "tags": [
        "quis",
        "et",
        "in",
        "quis",
        "duis",
        "eu",
        "eu"
      ],
      "friends": [
        {
          "id": 0,
          "name": "Kara Wong"
        },
        {
          "id": 1,
          "name": "Delia Mcintosh"
        },
        {
          "id": 2,
          "name": "Elnora Soto"
        }
      ],
      "greeting": "Hello, Rachelle Chavez! You have 3 unread messages.",
      "favoriteFruit": "banana"
    },
    {
      "_id": "666f5e37d504e623434e3b3e",
      "index": 6,
      "guid": "c8e6dbab-27ff-4627-99f3-1c92b7264639",
      "isActive": false,
      "balance": "$1,748.35",
      "picture": "http://placehold.it/32x32",
      "age": 24,
      "eyeColor": "brown",
      "name": "Harriett Juarez",
      "gender": "female",
      "company": "KNOWLYSIS",
      "email": "harriettjuarez@knowlysis.com",
      "phone": "+1 (856) 472-3355",
      "address": "527 Radde Place, Coaldale, Northern Mariana Islands, 2165",
      "about": "Elit cupidatat amet et pariatur eiusmod esse. Reprehenderit veniam adipisicing elit tempor exercitation occaecat reprehenderit deserunt voluptate tempor culpa est. Ipsum qui culpa nisi esse eu. Velit ut aliqua in sit mollit adipisicing nisi est nisi. Id consectetur Lorem irure cillum aliquip fugiat id culpa ut incididunt.\r\n",
      "registered": "2020-12-14T02:09:03 -01:00",
      "latitude": -32.918002,
      "longitude": -130.789005,
      "tags": [
        "laboris",
        "magna",
        "cupidatat",
        "pariatur",
        "adipisicing",
        "nostrud",
        "laborum"
      ],
      "friends": [
        {
          "id": 0,
          "name": "Jeannie Hanson"
        },
        {
          "id": 1,
          "name": "Melody Thompson"
        },
        {
          "id": 2,
          "name": "Isabel Rivera"
        }
      ],
      "greeting": "Hello, Harriett Juarez! You have 9 unread messages.",
      "favoriteFruit": "apple"
    }
  ]
}